immudb/__init__.py
immudb/client.py
immudb/constants.py
immudb/dataconverter.py
immudb/datatypes.py
immudb/datatypesv2.py
immudb/exceptions.py
immudb/generic_client_interceptor.py
immudb/grpcutils.py
immudb/printable.py
immudb/rootService.py
immudb/streamsutils.py
immudb/typeconv.py
immudb/database/__init__.py
immudb/database/meta.py
immudb/embedded/__init__.py
immudb/embedded/ahtree/__init__.py
immudb/embedded/ahtree/verification.py
immudb/embedded/htree/__init__.py
immudb/embedded/htree/htree.py
immudb/embedded/store/__init__.py
immudb/embedded/store/immustore.py
immudb/embedded/store/kv_metadata.py
immudb/embedded/store/ongoing_tx.py
immudb/embedded/store/tx.py
immudb/embedded/store/tx_metadata.py
immudb/embedded/store/verification.py
immudb/grpc/__init__.py
immudb/grpc/schema_pb2.py
immudb/grpc/schema_pb2_grpc.py
immudb/handler/__init__.py
immudb/handler/batchGet.py
immudb/handler/batchSet.py
immudb/handler/changePassword.py
immudb/handler/changePermission.py
immudb/handler/createDatabase.py
immudb/handler/createUser.py
immudb/handler/currentRoot.py
immudb/handler/databaseList.py
immudb/handler/deleteKeys.py
immudb/handler/execAll.py
immudb/handler/get.py
immudb/handler/health.py
immudb/handler/healthcheck.py
immudb/handler/history.py
immudb/handler/listUsers.py
immudb/handler/listtables.py
immudb/handler/reference.py
immudb/handler/scan.py
immudb/handler/setValue.py
immudb/handler/sqldescribe.py
immudb/handler/sqlexec.py
immudb/handler/sqlquery.py
immudb/handler/transaction.py
immudb/handler/txbyid.py
immudb/handler/useDatabase.py
immudb/handler/verifiedGet.py
immudb/handler/verifiedSQLGet.py
immudb/handler/verifiedSet.py
immudb/handler/verifiedreference.py
immudb/handler/verifiedtxbyid.py
immudb/handler/verifiedzadd.py
immudb/handler/zadd.py
immudb/handler/zscan.py
immudb/schema/__init__.py
immudb/schema/database_protoconv.py
immudb_py-1.5.0.dist-info/LICENSE
immudb_py-1.5.0.dist-info/METADATA
immudb_py-1.5.0.dist-info/WHEEL
immudb_py-1.5.0.dist-info/top_level.txt
immudb_py-1.5.0.dist-info/RECORD
