Metadata-Version: 2.1
Name: immudb-py
Version: 1.5.0
Summary: Python SDK for Immudb
Home-page: https://github.com/codenotary/immudb-py
Author: Codenotary
License: Apache License Version 2.0
Keywords: immudb,immutable
Platform: UNKNOWN
Classifier: Intended Audience :: Developers
Classifier: Topic :: Software Development :: Build Tools
Classifier: License :: OSI Approved :: Apache Software License
Classifier: Operating System :: OS Independent
Classifier: Programming Language :: Python :: 3
Classifier: Programming Language :: Python :: 3.6
Classifier: Programming Language :: Python :: 3.7
Classifier: Programming Language :: Python :: 3.8
Requires-Python: >=3.8
License-File: LICENSE
Requires-Dist: appier (>=1.32.0)
Requires-Dist: cachetools (>=5.3.3)
Requires-Dist: certifi (>=2024.2.2)
Requires-Dist: charset-normalizer (>=3.3.2)
Requires-Dist: ecdsa (>=0.18.0)
Requires-Dist: google-api-core (>=2.18.0)
Requires-Dist: google-api-python-client (>=2.123.0)
Requires-Dist: google-api (>=0.1.12)
Requires-Dist: google-auth-httplib2 (>=0.2.0)
Requires-Dist: google-auth (>=2.29.0)
Requires-Dist: googleapis-common-protos (>=1.63.0)
Requires-Dist: grpcio (>=1.62.1)
Requires-Dist: httplib2 (>=0.22.0)
Requires-Dist: idna (>=3.6)
Requires-Dist: proto-plus (>=1.23.0)
Requires-Dist: protobuf (>=4.25.3)
Requires-Dist: pyasn1 (>=0.6.0)
Requires-Dist: pyasn1-modules (>=0.4.0)
Requires-Dist: pyparsing (>=3.1.2)
Requires-Dist: requests (>=2.31.0)
Requires-Dist: rsa (>=4.9)
Requires-Dist: six (>=1.16.0)
Requires-Dist: uritemplate (>=4.1.1)
Requires-Dist: urllib3 (>=2.2.1)
